foxypack-0.0.11.dist-info/METADATA
foxypack-0.0.11.dist-info/WHEEL
foxypack-0.0.11.dist-info/entry_points.txt
foxypack-0.0.11.dist-info/licenses/LICENSE
foxypack/__init__.py
foxypack/controller.py
foxypack/exceptions.py
foxypack/foxypack_abc/__init__.py
foxypack/foxypack_abc/answers.py
foxypack/foxypack_abc/foxyanalysis.py
foxypack/foxypack_abc/foxystat.py
foxypack/py.typed
foxypack-0.0.11.dist-info/RECORD
